megrok/strictrequire/README.rst
megrok/strictrequire/__init__.py
megrok/strictrequire/configure.zcml
megrok/strictrequire/meta.py
megrok/strictrequire/tests/__init__.py
megrok/strictrequire/tests/checkrequire.rst
megrok/strictrequire/tests/fixtures.py
megrok/strictrequire/tests/ftesting.zcml
megrok/strictrequire/tests/test.py
megrok_strictrequire-5.2.dist-info/licenses/LICENSE.txt
megrok_strictrequire-5.2.dist-info/METADATA
megrok_strictrequire-5.2.dist-info/WHEEL
megrok_strictrequire-5.2.dist-info/top_level.txt
megrok_strictrequire-5.2.dist-info/RECORD
