Metadata-Version: 2.4
Name: megrok.strictrequire
Version: 5.2
Summary: Checks that all grokked "view-like" components require a permission.
Author-email: The Health Agency <zope-dev@zope.dev>
Maintainer-email: Plone Foundation and contributors <zope-dev@zope.dev>
License-Expression: ZPL-2.1
Project-URL: Source, https://github.com/zopefoundation/megrok.strictrequire/
Classifier: Development Status :: 5 - Production/Stable
Classifier: Natural Language :: English
Classifier: Programming Language :: Python
Classifier: Programming Language :: Python :: 3
Classifier: Programming Language :: Python :: 3.10
Classifier: Programming Language :: Python :: 3.11
Classifier: Programming Language :: Python :: 3.12
Classifier: Programming Language :: Python :: 3.13
Classifier: Programming Language :: Python :: 3.14
Classifier: Programming Language :: Python :: Implementation :: CPython
Classifier: Programming Language :: Python :: Implementation :: PyPy
Requires-Python: >=3.10
License-File: LICENSE.txt
Requires-Dist: setuptools
Requires-Dist: martian
Requires-Dist: grok>=5.0a1
Provides-Extra: test
Requires-Dist: zope.component; extra == "test"
Requires-Dist: zope.interface; extra == "test"
Requires-Dist: zope.securitypolicy; extra == "test"
Requires-Dist: zope.testing; extra == "test"
Requires-Dist: zope.testrunner>=6.4; extra == "test"
Dynamic: license-file
